cache_management/main_memory.v
module main_memory(
	input wire clk,
	input wire rst,
	input wire mem_req,
	input wire mem_write,
	input wire [31:0] mem_addr,
	input wire [31:0] mem_wdata,
	output reg [127:0] mem_rdata, // From Main Memory to CPU (new Cache)
	output wire mem_ready
);
	
	// To create Latency
	localparam IDLE = 2'b00;
	localparam ACCESS = 2'b01;
	localparam READY = 2'b10;
	reg [3:0] delay_counter;
	
	reg [1:0] state, next_state;
	
	
	reg [127:0] ram [0:15];
	integer i; // Dummy Data
	initial begin
		for(i = 0; i < 16; i = i + 1) begin
			ram[i] = {32'h44444444, 32'h33333333, 32'h22222222, 32'h11111111};
		end
	end

	// Ram Indexing
	wire [3:0] offset = mem_addr[3:0]; // There are 16 byte in 128 bit, we parse that
	wire [3:0] ram_index = mem_addr[7:4]; // 16(2^4)x128 ram indexing
	
	assign mem_ready = (state == READY);

	always @(posedge clk) begin
		if(rst) begin
			state <= IDLE;
			delay_counter <= 4'b0000;
		end
		else begin
			state <= next_state;
			case(state)
				IDLE: begin
					delay_counter <= 4'b0000;
				end
				ACCESS: begin
					delay_counter <= delay_counter + 1'b1;
					if(delay_counter == 4'b1001) begin
						if(mem_write == 1'b1) begin // Cache is writen from Cache to Main Memory
							if(offset[3:2] == 2'b00) ram[ram_index][31:0] <= mem_wdata;
							else if(offset[3:2] == 2'b01) ram[ram_index][63:32] <= mem_wdata;
							else if(offset[3:2] == 2'b10) ram[ram_index][95:64] <= mem_wdata;
							else ram[ram_index][127:96] <= mem_wdata;
						end
						else begin // Ram's data is writen to Cache
							mem_rdata <= ram[ram_index];
						end
					end
				end
				READY: begin
					// Just holds old datas with stability
				end
			endcase
		end
	end
	
	always @(*) begin
		next_state = state;
		
		case(state)
			IDLE: begin
				if(mem_req) begin
					next_state = ACCESS;
				end
				else begin
					next_state = IDLE;
				end
			end
			ACCESS: begin
				if(delay_counter == 4'b1001) begin
					next_state = READY;
				end
				else begin
					next_state = ACCESS;
				end
			end
			READY: begin
				if(!mem_req) begin // Cache finished its work
					next_state = IDLE;
				end
				else begin
					next_state = READY;
				end
			end
			default: next_state = IDLE;
		endcase
	end
endmodule

cache_management/src/cache.v
module cache(
	input wire clk,
	input wire rst,
	input wire cpu_req,
	input wire cpu_write,
	input wire [31:0] cpu_addr,
	input wire [31:0] cpu_wdata,
	output wire [31:0] cpu_rdata,
	output wire cpu_ready,
	output wire mem_req,
	output wire [31:0] mem_addr,
	output wire [31:0] mem_wdata,
	output wire mem_write,
	input wire [127:0] mem_rdata,
	input wire mem_ready
);

	localparam IDLE = 2'b00;
	localparam COMPARE = 2'b01;
	localparam ALLOCATE = 2'b10;
	localparam WRITE_MEM =2'b11;
	
	reg [1:0] state,next_state;
	
	reg valid_array [0:7]; // First bit of Cache Line - NOTE:There are 8 Cache Line
	reg [24:0] tag_array [0:7]; // Tag of Cache Line
	reg [127:0] data_array [0:7]; // Cache Line
	
	// cpu_addr parsing
	wire [3:0] offset = cpu_addr[3:0]; // For 16 (2^4) byte Cache Line
	wire [2:0] index = cpu_addr[6:4]; // For 8 (2^3) Cache Row
	wire [24:0] tag = cpu_addr[31:7]; // The other 25 bit
	
	wire valid_bit = valid_array[index]; // The valid values provide us to be sure datas correctness.
	wire [24:0] stored_tag = tag_array[index]; 
	
	wire hit = ((valid_bit == 1'b1) && (stored_tag == tag));
	
	assign mem_addr = {cpu_addr[31:4] , 4'b0000}; // Mod(%) 0f 16 to get 128 bit Cache Line
	assign mem_wdata = cpu_wdata; // Data goes from CPU to Cache and MainMemory
	
	
	wire [127:0] current_cache_line = data_array[index];
	// If you want to read cpu_rdata, There is 4(128/32) cache option and them offsets just can start(word-alligned) with 0000(0), 0100(4), 1000(8), 1100(12)
	// So we can eleminate easily cache that includes wanted data.
	// A cache line(128-bit) stores 4 cache(32-bit), so we parse it.
	assign cpu_rdata = ( (offset[3:2]==2'b00) ? current_cache_line[31:0]:
								(offset[3:2]==2'b01) ? current_cache_line[63:32]:
								(offset[3:2]==2'b10) ? current_cache_line[95:64]:
								current_cache_line[127:96] );
								
	assign mem_req = (state == ALLOCATE) || (state == WRITE_MEM);
	assign mem_write = (state == WRITE_MEM);
	assign cpu_ready = ((state == COMPARE) && hit && !cpu_write) || ((state == WRITE_MEM) && mem_ready);
	
	
	integer i; // For valid_array reset
	
	always @(posedge clk) begin
		if(rst) begin
			state <= IDLE;
			for(i=0; i<8; i=i+1) begin
				valid_array[i] <= 1'b0;
				// we cannot do directly valid_array = 8'b00000000; because the array 7x1 not 1x7.
			end
		end
		else begin
			state <= next_state;
			if((state == ALLOCATE) && (mem_ready == 1'b1)) begin
				valid_array[index] <= 1'b1; // When the conditions are provided, we hit Cache Line.
				tag_array[index] <= tag; // The hitted datas can be usable yet.
				data_array[index] <= mem_rdata; // The data that comes form the memory.
			end
			
			// The condition provides to write new datas to Cache
			if((state == COMPARE) && (hit) && (cpu_write == 1'b1)) begin
				if(offset[3:2] == 2'b00) data_array[index][31:0] <= cpu_wdata;
				else if(offset[3:2] == 2'b01) data_array[index][63:32] <= cpu_wdata;
				else if(offset[3:2] == 2'b10) data_array[index][95:64] <= cpu_wdata;
				else data_array[index][127:96] <= cpu_wdata;
			end
			
		end
	end
	
	
	always @(*) begin
		next_state = state;
		
		case (state)
			IDLE: begin
				if(cpu_req) begin
					next_state=COMPARE;
				end
				else begin
					next_state=IDLE;
				end
			end
			COMPARE: begin
				if(!hit) begin // When there is no wanted data in the cache, we have to allocate
					next_state=ALLOCATE;
				end
				else begin
					if(cpu_write) begin
						next_state = WRITE_MEM;
					end
					else begin
						next_state=IDLE;
					end
				end
			end
			ALLOCATE: begin
				if(mem_ready) begin
					next_state=COMPARE;
				end
			end
			WRITE_MEM: begin
				if(mem_ready) begin // These ready signals provide to start-stop communication.
					next_state = IDLE;
				end
			end
		endcase
	end
	
endmodule

cache_management/src/testbench.v
`timescale 1ns/1ps
module testbench;
	reg clk;
	reg rst;
	reg cpu_req;
	reg cpu_write;
	reg [31:0] cpu_addr;
	reg [31:0] cpu_wdata;
	
	wire [31:0] cpu_rdata;
	wire cpu_ready;
	
	wire mem_req;
	wire [31:0] mem_addr;
	wire [31:0] mem_wdata;
	wire mem_write;
	wire [127:0] mem_rdata;
	wire mem_ready;

	cache cache_uut(
		.clk(clk),
		.rst(rst),
		.cpu_req(cpu_req),
		.cpu_write(cpu_write),
		.cpu_addr(cpu_addr),
		.cpu_wdata(cpu_wdata),
		.cpu_rdata(cpu_rdata),
		.cpu_ready(cpu_ready),
		.mem_req(mem_req),
		.mem_addr(mem_addr),
		.mem_wdata(mem_wdata),
		.mem_write(mem_write),
		.mem_rdata(mem_rdata),
		.mem_ready(mem_ready)
	);
	main_memory mem_uut(
		.clk(clk),
		.rst(rst),
		.mem_req(mem_req),
		.mem_write(mem_write),
		.mem_addr(mem_addr),
		.mem_wdata(mem_wdata),
		.mem_rdata(mem_rdata),
		.mem_ready(mem_ready)
	);
	
	always #5 clk =~clk;
	
	initial begin
		// Waveform
		$dumpfile("sim_cache_management.vcd"); 
		$dumpvars(0, testbench);

		clk = 0;
		rst = 1;
		cpu_req = 0;
		cpu_write = 0;
		cpu_addr = 0;
		cpu_wdata = 0;

		#20;
		rst = 0;
		#10;

		
		// ---------------------------------------------------------
		// Scenario 1: Cache Miss 
		// CPU wants an unreaden data address. 
		// Main Memory occurs 10 Clock Cycle latency.
		// ---------------------------------------------------------
		cpu_addr = 32'h000000A4; 
		cpu_write = 0;           // Process  type: Reading
		cpu_req = 1;             // CPU start signal
		
		// CPU waits (Stall) until cpu_ready = 1
		wait(cpu_ready == 1);
		@(posedge clk);          // Just wait 1 more Clock Cycle to catch Singal correctly.
		cpu_req = 0;             // CPU closed
		
		#30; // To clear obtain

		// ---------------------------------------------------------
		// Scenario 2: Cache Hit 
		// Data in the Cache. Cpu doesn't send any signal to Main Memory.
		// Process should be completed in 1 Clock Cycle
		// ---------------------------------------------------------
		cpu_addr = 32'h000000A4; // Same address
		cpu_write = 0;           
		cpu_req = 1;             
		
		while (cpu_ready == 0) begin
			@(posedge clk);
		end
		cpu_req = 0;
		
		#30;

		// ---------------------------------------------------------
		// Scenario 3: Write-Through
		// CPU wants to write new data at the same address
		// First Cache delibaretly update, then wait to write to Main Memory
		// ---------------------------------------------------------
		cpu_addr = 32'h000000A4; 
		cpu_wdata = 32'hDEADBEEF; // New data
		cpu_write = 1;            // Process type: Write
		cpu_req = 1;
		
		wait(cpu_ready == 1);
		@(posedge clk);
		cpu_req = 0;
		cpu_write = 0;

		#50;
		
		$finish;
	end
endmodule

sim_cache_management.vcd
$date
	Mon Aug 24 18:09:07 2026
$end
$version
	Icarus Verilog
$end
$timescale
	1ps
$end
$scope module testbench $end
$var wire 1 ! mem_write $end
$var wire 32 " mem_wdata [31:0] $end
$var wire 1 # mem_req $end
$var wire 1 $ mem_ready $end
$var wire 128 % mem_rdata [127:0] $end
$var wire 32 & mem_addr [31:0] $end
$var wire 1 ' cpu_ready $end
$var wire 32 ( cpu_rdata [31:0] $end
$var reg 1 ) clk $end
$var reg 32 * cpu_addr [31:0] $end
$var reg 1 + cpu_req $end
$var reg 32 , cpu_wdata [31:0] $end
$var reg 1 - cpu_write $end
$var reg 1 . rst $end
$scope module cache_uut $end
$var wire 1 ) clk $end
$var wire 32 / cpu_addr [31:0] $end
$var wire 1 ' cpu_ready $end
$var wire 1 + cpu_req $end
$var wire 32 0 cpu_wdata [31:0] $end
$var wire 1 - cpu_write $end
$var wire 128 1 current_cache_line [127:0] $end
$var wire 1 2 hit $end
$var wire 1 # mem_req $end
$var wire 32 3 mem_wdata [31:0] $end
$var wire 1 . rst $end
$var wire 25 4 stored_tag [24:0] $end
$var wire 1 5 valid_bit $end
$var wire 25 6 tag [24:0] $end
$var wire 4 7 offset [3:0] $end
$var wire 1 ! mem_write $end
$var wire 1 $ mem_ready $end
$var wire 128 8 mem_rdata [127:0] $end
$var wire 32 9 mem_addr [31:0] $end
$var wire 3 : index [2:0] $end
$var wire 32 ; cpu_rdata [31:0] $end
$var parameter 2 < ALLOCATE $end
$var parameter 2 = COMPARE $end
$var parameter 2 > IDLE $end
$var parameter 2 ? WRITE_MEM $end
$var reg 2 @ next_state [1:0] $end
$var reg 2 A state [1:0] $end
$var integer 32 B i [31:0] $end
$upscope $end
$scope module mem_uut $end
$var wire 1 ) clk $end
$var wire 32 C mem_addr [31:0] $end
$var wire 1 # mem_req $end
$var wire 32 D mem_wdata [31:0] $end
$var wire 1 ! mem_write $end
$var wire 1 . rst $end
$var wire 4 E ram_index [3:0] $end
$var wire 4 F offset [3:0] $end
$var wire 1 $ mem_ready $end
$var parameter 2 G ACCESS $end
$var parameter 2 H IDLE $end
$var parameter 2 I READY $end
$var reg 4 J delay_counter [3:0] $end
$var reg 128 K mem_rdata [127:0] $end
$var reg 2 L next_state [1:0] $end
$var reg 2 M state [1:0] $end
$var integer 32 N i [31:0] $end
$upscope $end
$upscope $end
$enddefinitions $end
$comment Show the parameter values. $end
$dumpall
b10 I
b0 H
b1 G
b11 ?
b0 >
b1 =
b10 <
$end
#0
$dumpvars
b10000 N
bx M
bx L
bx K
bx J
b0 F
b0 E
b0 D
b0 C
bx B
bx A
bx @
bx ;
b0 :
b0 9
bx 8
b0 7
b0 6
x5
bx 4
b0 3
x2
bx 1
b0 0
b0 /
1.
0-
b0 ,
0+
b0 *
0)
bx (
x'
b0 &
bx %
x$
x#
b0 "
x!
$end
#5000
0'
02
0#
b0 L
b0 @
05
0!
b0 A
b0 J
0$
b0 M
b1000 B
1)
#10000
0)
#15000
b1000 B
1)
#20000
0)
0.
#25000
1)
#30000
b1010 E
b10100000 &
b10100000 9
b10100000 C
b1 @
b100 7
b10 :
b1 6
0)
1+
b10100100 *
b10100100 /
#35000
b10 @
b1 A
1)
#40000
0)
#45000
b1 L
1#
b10 A
1)
#50000
0)
#55000
b1 M
1)
#60000
0)
#65000
b1 J
1)
#70000
0)
#75000
b10 J
1)
#80000
0)
#85000
b11 J
1)
#90000
0)
#95000
b100 J
1)
#100000
0)
#105000
b101 J
1)
#110000
0)
#115000
b110 J
1)
#120000
0)
#125000
b111 J
1)
#130000
0)
#135000
b1000 J
1)
#140000
0)
#145000
b10 L
b1001 J
1)
#150000
0)
#155000
b1 @
b1000001001000110100000100100011001101000001001000110100000100100010001101000001001000110100000100010010001101000001001000110100 %
b1000001001000110100000100100011001101000001001000110100000100100010001101000001001000110100000100010010001101000001001000110100 8
b1000001001000110100000100100011001101000001001000110100000100100010001101000001001000110100000100010010001101000001001000110100 K
b1010 J
1$
b10 M
1)
#160000
0)
#165000
1'
b100011010000010010001101000001 (
b100011010000010010001101000001 ;
b0 L
12
b0 @
0#
b1000001001000110100000100100011001101000001001000110100000100100010001101000001001000110100000100010010001101000001001000110100 1
b1 4
15
b1 A
1)
#170000
0)
#175000
0'
0$
b0 M
b0 A
b0 @
0+
1)
#180000
0)
#185000
b0 J
1)
#190000
0)
#195000
1)
#200000
0)
#205000
1'
b1 A
b0 @
1)
1+
#210000
0)
#215000
0'
b0 A
b0 @
0+
1)
#220000
0)
#225000
1)
#230000
0)
#235000
1)
#240000
0)
#245000
b1 A
b11 @
1)
1+
1-
b11011110101011011011111011101111 "
b11011110101011011011111011101111 3
b11011110101011011011111011101111 D
b11011110101011011011111011101111 ,
b11011110101011011011111011101111 0
#250000
0)
#255000
b11011110101011011011111011101111 (
b11011110101011011011111011101111 ;
b1 L
1#
b1000001001000110100000100100011001101000001001000110100000100101101111010101101101111101110111100010010001101000001001000110100 1
1!
b11 A
1)
#260000
0)
#265000
b1 M
1)
#270000
0)
#275000
b1 J
1)
#280000
0)
#285000
b10 J
1)
#290000
0)
#295000
b11 J
1)
#300000
0)
#305000
b100 J
1)
#310000
0)
#315000
b101 J
1)
#320000
0)
#325000
b110 J
1)
#330000
0)
#335000
b111 J
1)
#340000
0)
#345000
b1000 J
1)
#350000
0)
#355000
b10 L
b1001 J
1)
#360000
0)
#365000
1'
b0 @
b1010 J
1$
b10 M
1)
#370000
0)
#375000
b0 L
0'
0#
0!
b0 A
b0 @
0-
0+
1)
#380000
0)
#385000
0$
b0 M
1)
#390000
0)
#395000
b0 J
1)
